lollipop/__init__.py
lollipop/compat.py
lollipop/errors.py
lollipop/ordereddict.py
lollipop/type_registry.py
lollipop/types.py
lollipop/utils.py
lollipop/validators.py
lollipop-1.1.8.dist-info/LICENSE
lollipop-1.1.8.dist-info/METADATA
lollipop-1.1.8.dist-info/WHEEL
lollipop-1.1.8.dist-info/top_level.txt
lollipop-1.1.8.dist-info/RECORD
