Metadata-Version: 2.1
Name: lollipop
Version: 1.1.8
Summary: Data serialization and validation library
Home-page: https://github.com/maximkulkin/lollipop
Author: Maxim Kulkin
Author-email: maxim.kulkin@gmail.com
License: MIT
Keywords: serialization,rest,json,api,marshal,marshalling,deserialization,validation,schema,marshmallow
Classifier: Development Status :: 5 - Production/Stable
Classifier: Intended Audience :: Developers
Classifier: License :: OSI Approved :: MIT License
Classifier: Programming Language :: Python :: 2
Classifier: Programming Language :: Python :: 2.7
Classifier: Programming Language :: Python :: 3
Classifier: Programming Language :: Python :: 3.3
Classifier: Programming Language :: Python :: 3.4
Classifier: Programming Language :: Python :: 3.5
Classifier: Programming Language :: Python :: 3.6
Classifier: Programming Language :: Python :: Implementation :: CPython
Classifier: Programming Language :: Python :: Implementation :: PyPy
License-File: LICENSE
